gocept.httpserverlayer-4.0-py3.7-nspkg.pth
gocept/httpserverlayer/__init__.py
gocept/httpserverlayer/testing.py
gocept/httpserverlayer/custom/__init__.py
gocept/httpserverlayer/plonetestingzope/__init__.py
gocept/httpserverlayer/plonetestingzope/testing.py
gocept/httpserverlayer/plonetestingzope/testing.zcml
gocept/httpserverlayer/plonetestingzope/tests/__init__.py
gocept/httpserverlayer/plonetestingzope/tests/test_zope2.py
gocept/httpserverlayer/static/__init__.py
gocept/httpserverlayer/static/tests/__init__.py
gocept/httpserverlayer/static/tests/test_static.py
gocept/httpserverlayer/tests/__init__.py
gocept/httpserverlayer/tests/isolation/__init__.py
gocept/httpserverlayer/tests/isolation/configure.zcml
gocept/httpserverlayer/tests/isolation/views.py
gocept/httpserverlayer/wsgi/__init__.py
gocept/httpserverlayer/wsgi/tests.py
gocept/httpserverlayer/zopeappwsgi/__init__.py
gocept/httpserverlayer/zopeappwsgi/fixtures.py
gocept/httpserverlayer/zopeappwsgi/testing.py
gocept/httpserverlayer/zopeappwsgi/testing.zcml
gocept/httpserverlayer/zopeappwsgi/tests.py
gocept.httpserverlayer-4.0.dist-info/LICENSE.txt
gocept.httpserverlayer-4.0.dist-info/METADATA
gocept.httpserverlayer-4.0.dist-info/WHEEL
gocept.httpserverlayer-4.0.dist-info/entry_points.txt
gocept.httpserverlayer-4.0.dist-info/namespace_packages.txt
gocept.httpserverlayer-4.0.dist-info/top_level.txt
gocept.httpserverlayer-4.0.dist-info/RECORD
