Metadata-Version: 2.1
Name: gocept.httpserverlayer
Version: 4.0
Summary: HTTP server integration for testing
Home-page: https://github.com/gocept/gocept.httpserverlayer
Author: gocept <mail@gocept.com>
Author-email: mail@gocept.com
License: ZPL 2.1
Keywords: HTTP server Plone testing zope.testrunner layer Zope
Platform: UNKNOWN
Classifier: Development Status :: 5 - Production/Stable
Classifier: Framework :: Zope :: 3
Classifier: Framework :: Zope :: 4
Classifier: Framework :: Zope :: 5
Classifier: Intended Audience :: Developers
Classifier: License :: OSI Approved :: Zope Public License
Classifier: Operating System :: OS Independent
Classifier: Programming Language :: Python :: 3
Classifier: Programming Language :: Python :: 3 :: Only
Classifier: Programming Language :: Python :: 3.6
Classifier: Programming Language :: Python :: 3.7
Classifier: Programming Language :: Python :: 3.8
Classifier: Programming Language :: Python :: 3.9
Classifier: Programming Language :: Python :: Implementation :: CPython
Classifier: Topic :: Internet :: WWW/HTTP :: HTTP Servers
Classifier: Topic :: Software Development :: Testing
Requires-Dist: setuptools
Requires-Dist: plone.testing
Provides-Extra: plonetestingzope
Requires-Dist: Zope (>=4.0b1) ; extra == 'plonetestingzope'
Requires-Dist: plone.testing[zope] (>=7.0dev0) ; extra == 'plonetestingzope'
Provides-Extra: test
Requires-Dist: shoobx.junitxml ; extra == 'test'
Provides-Extra: zopeappwsgi
Requires-Dist: zope.app.wsgi (>=4) ; extra == 'zopeappwsgi'
